LICENSE
MANIFEST.in
README.md
requirements.txt
setup.cfg
setup.py
django_mp_faq.egg-info/PKG-INFO
django_mp_faq.egg-info/SOURCES.txt
django_mp_faq.egg-info/dependency_links.txt
django_mp_faq.egg-info/requires.txt
django_mp_faq.egg-info/top_level.txt
faq/__init__.py
faq/admin.py
faq/models.py
faq/translation.py
faq/locale/ru/LC_MESSAGES/django.mo
faq/locale/ru/LC_MESSAGES/django.po
faq/locale/uk/LC_MESSAGES/django.mo
faq/locale/uk/LC_MESSAGES/django.po
faq/migrations/0001_initial.py
faq/migrations/0002_add_question_order.py
faq/migrations/__init__.py
faq/templatetags/__init__.py
faq/templatetags/faq.py