Metadata-Version: 2.1
Name: django-mp-faq
Version: 2.0.3
Summary: Simple Django FAQ app
Home-page: https://github.com/pmaigutyak/mp-faq
Author: Paul Maigutyak
Author-email: pmaigutyak@gmail.com
License: MIT
Download-URL: https://github.com/pmaigutyak/mp-faq/archive/2.0.3.tar.gz
Platform: UNKNOWN
License-File: LICENSE
